LICENSE
MANIFEST.in
README.rst
ann.png
setup.cfg
setup.py
annoy/__init__.py
annoy_dm.egg-info/PKG-INFO
annoy_dm.egg-info/SOURCES.txt
annoy_dm.egg-info/dependency_links.txt
annoy_dm.egg-info/top_level.txt
src/annoylib.h
src/annoymodule.cc
src/kissrandom.h
src/mman.h